discord_framework/__init__.py
discord_framework/api.py
discord_framework/discord_framework.py
discord_framework-1.14.0.dist-info/METADATA
discord_framework-1.14.0.dist-info/WHEEL
discord_framework-1.14.0.dist-info/RECORD
