Metadata-Version: 2.3
Name: discord-framework
Version: 1.14.0
Summary: Framework for creating Discord bots
Author: Derek 'Vlek' McCammond
Requires-Python: >=3.9,<4.0
Classifier: Programming Language :: Python :: 3
Classifier: Programming Language :: Python :: 3.9
Classifier: Programming Language :: Python :: 3.10
Classifier: Programming Language :: Python :: 3.11
Classifier: Programming Language :: Python :: 3.12
Classifier: Programming Language :: Python :: 3.13
Requires-Dist: async-timeout (>=4.0.3,<5.0.0)
Requires-Dist: discord.py (>=2.4.0,<3.0.0)
Requires-Dist: pytest-asyncio (>=0.26.0,<0.27.0)
